CHANGELOG.txt
LICENSE.txt
MANIFEST.in
README.txt
setup.py
maheshbasiccalculator/__init_.py
maheshbasiccalculator.egg-info/PKG-INFO
maheshbasiccalculator.egg-info/SOURCES.txt
maheshbasiccalculator.egg-info/dependency_links.txt
maheshbasiccalculator.egg-info/top_level.txt